{"name":"Desclocar-posicionamento-lua-aegisub","tagline":"Serve para desclocar \\pos, \\move, \\org e \\clip","body":"Desclocar-Posicionamento-Aegisub\r\n================================\r\n\r\nServe para desclocar \\pos, \\move, \\org e \\clip\r\n\r\n\r\nPor fazer\r\n-----------------\r\n* Creio que já está tudo feito, mas estarei disposto a melhorar se houver dicas para tal.\r\n\r\n\r\nComo instalar\r\n--------------\r\n\r\nLoad Automático\r\n\r\n1. Transferir pos_shift_x.0-pt.lua\r\n2. Colocar esse ficheiro na pasta _autoload_ situada dentro da pasta _automation_ que por sua vez está presenta na sua pasta de instalação do aegisub\r\n\r\n\r\nLoad Manual\r\n\r\n1. Transferir pos_shift_x.0_pt.lua e guarde-o onde bem desejar\r\n2. Com o Aegisub aberto, quando desejar usá-lo terá de clicar em Automatização -> Automatização...\r\n3. Clicar de seguida em _Adicionar_ e ir ao local onde se encontra o pos_shift_x.0_pt.lua\r\n\r\n\r\nComo usar\r\n---------\r\n\r\nBasta seleccionar todas as linhas na qual desejamos reposicionar seja o \\pos e/ou \\move e/ou \\org e/ou \\clip,\r\ncolocar os valores, valores estes que em positivo serve para descer no eixo dos y e mover para a direita no eixo dos x,\r\ne para subir no eixo dos y e mover para a esquerda do eixo do x basta usar valores negativos.\r\n","google":"","note":"Don't delete this file! It's used internally to help with page regeneration."}